{"lastUpdated": "2026-03-31T14:15:21.667796+00:00", "maps": {"Abyss": {"picked": 57, "banned": 72, "decider": 15}, "Split": {"picked": 49, "banned": 64, "decider": 33}, "Haven": {"picked": 47, "banned": 79, "decider": 20}, "Pearl": {"picked": 44, "banned": 92, "decider": 9}, "Bind": {"picked": 43, "banned": 75, "decider": 28}, "Breeze": {"picked": 43, "banned": 78, "decider": 25}, "Corrode": {"picked": 35, "banned": 93, "decider": 16}, "Lotus": {"picked": 1, "banned": 1, "decider": 0}, "Fracture": {"picked": 1, "banned": 1, "decider": 0}}}